ryskV12/__init__.py
ryskV12/client.py
ryskV12/models.py
ryskV12/scripts/fetch_latest_release.sh
ryskv12-3.0.1.dist-info/LICENSE
ryskv12-3.0.1.dist-info/METADATA
ryskv12-3.0.1.dist-info/WHEEL
ryskv12-3.0.1.dist-info/RECORD
