Metadata-Version: 2.1
Name: ryskV12
Version: 3.0.1
Summary: Python sdk to interact with Rysk v12
License: MIT
Author: thundering-silence
Author-email: jack@rysk.finance
Requires-Python: >=3.11,<4.0
Classifier: License :: OSI Approved :: MIT License
Classifier: Programming Language :: Python :: 3
Classifier: Programming Language :: Python :: 3.11
